{
    "className": "Victron",
    "protocol": "TCP",
    "endianness": "LittleEndian",
    "errorLimitUntilNotReachable": 5,
    "checkReachableRegister": "inverterCurrentPowerPv",
    "enums": [
    ],
    "blocks": [
        {
            "id": "system",
            "readSchedule": "update",
            "registers": [
                {
                    "id": "inverterCurrentPowerPv",
                    "address": 808,
                    "size": 1,
                    "type": "uint16",
                    "registerType": "holdingRegister",
                    "description": "Power of AC-Coupled PV Inverters on the output",
                    "unit": "W",
                    "defaultValue": "0",
                    "access": "RO"
                },
                {
                    "id": "dummy1",
                    "address": 809,
                    "size": 11,
                    "type": "raw",
                    "registerType": "holdingRegister",
                    "description": "none",
                    "access": "RO"
                },
                {
                    "id": "meterPowerA",
                    "address": 820,
                    "size": 1,
                    "type": "int16",
                    "registerType": "holdingRegister",
                    "description": "Phase A power from grid",
                    "unit": "W",
                    "defaultValue": "0",
                    "access": "RO"
                },
                {
                    "id": "meterPowerB",
                    "address": 821,
                    "size": 1,
                    "type": "int16",
                    "registerType": "holdingRegister",
                    "description": "Phase B power from grid",
                    "unit": "W",
                    "defaultValue": "0",
                    "access": "RO"
                },
                {
                    "id": "meterPowerC",
                    "address": 822,
                    "size": 1,
                    "type": "int16",
                    "registerType": "holdingRegister",
                    "description": "Phase A power from grid",
                    "unit": "W",
                    "defaultValue": "0",
                    "access": "RO"
                },
                {
                    "id": "dummy2",
                    "address": 823,
                    "size": 17,
                    "type": "raw",
                    "registerType": "holdingRegister",
                    "description": "none",
                    "access": "RO"
                },
                {
                    "id": "batteryVoltage",
                    "address": 840,
                    "size": 1,
                    "type": "uint16",
                    "registerType": "holdingRegister",
                    "description": "DC battery voltage",
                    "defaultValue": "0",
                    "staticScaleFactor": -1,
                    "unit": "V",
                    "access": "RO"
                },
                {
                    "id": "dummy3",
                    "address": 841,
                    "size": 1,
                    "type": "raw",
                    "registerType": "holdingRegister",
                    "description": "none",
                    "access": "RO"
                },
                {
                    "id": "batteryPower",
                    "address": 842,
                    "size": 1,
                    "type": "int16",
                    "registerType": "holdingRegister",
                    "description": "DC battery power, positive: charging, negative: discharging",
                    "unit": "W",
                    "defaultValue": "0",
                    "access": "RO"
                },
                {
                    "id": "batterySoc",
                    "address": 843,
                    "size": 1,
                    "type": "uint16",
                    "registerType": "holdingRegister",
                    "description": "Battery state of charge",
                    "unit": "%",
                    "defaultValue": "0",
                    "access": "RO"
                }
            ]
        },
        {
            "id": "battery",
            "readSchedule": "update",
            "registers": [
                {
                    "id": "batteryTemperature",
                    "address": 262,
                    "size": 1,
                    "type": "int16",
                    "registerType": "holdingRegister",
                    "description": "Battery temperature",
                    "staticScaleFactor": -1,
                    "unit": "°C",
                    "defaultValue": "0",
                    "access": "RO"
                },
                {
                    "id": "dummy4",
                    "address": 263,
                    "size": 46,
                    "type": "raw",
                    "registerType": "holdingRegister",
                    "description": "none",
                    "access": "RO"
                },
                {
                    "id": "batteryCapacity",
                    "address": 309,
                    "size": 1,
                    "type": "uint16",
                    "registerType": "holdingRegister",
                    "description": "battery capacity",
                    "staticScaleFactor": -1,
                    "unit": "Ah",
                    "defaultValue": "0",
                    "access": "RO"
                }
            ]
        },
        {
            "id": "pvinverter",
            "readSchedule": "update",
            "registers": [
                {
                    "id": "totalEnergyProducedA",
                    "address": 1046,
                    "size": 2,
                    "type": "uint32",
                    "registerType": "holdingRegister",
                    "description": "Phase A energy produced",
                    "staticScaleFactor": -2,
                    "unit": "kWh",
                    "defaultValue": "0",
                    "access": "RO"
                },
                {
                    "id": "totalEnergyProducedB",
                    "address": 1048,
                    "size": 2,
                    "type": "uint32",
                    "registerType": "holdingRegister",
                    "description": "Phase B energy produced",
                    "staticScaleFactor": -2,
                    "unit": "kWh",
                    "defaultValue": "0",
                    "access": "RO"
                },
                {
                    "id": "totalEnergyProducedC",
                    "address": 1050,
                    "size": 2,
                    "type": "uint32",
                    "registerType": "holdingRegister",
                    "description": "Phase C energy produced",
                    "staticScaleFactor": -2,
                    "unit": "kWh",
                    "defaultValue": "0",
                    "access": "RO"
                },
                {
                    "id": "dummy5",
                    "address": 1052,
                    "size": 12,
                    "type": "raw",
                    "registerType": "holdingRegister",
                    "description": "none",
                    "access": "RO"
                },
                {
                    "id": "inverterFrequency",
                    "address": 1064,
                    "size": 1,
                    "type": "uint16",
                    "registerType": "holdingRegister",
                    "description": "Daily PV generation",
                    "unit": "Hz",
                    "defaultValue": "0",
                    "staticScaleFactor": -2,
                    "access": "RO"
                }
            ]
        },
        {
            "id": "grid",
            "readSchedule": "update",
            "registers": [
                {
                    "id": "meterVoltageA",
                    "address": 2616,
                    "size": 1,
                    "type": "uint16",
                    "registerType": "holdingRegister",
                    "description": "Phase A voltage grid",
                    "unit": "V",
                    "defaultValue": "0",
                    "staticScaleFactor": -1,
                    "access": "RO"
                },
                {
                    "id": "meterCurrentA",
                    "address": 2617,
                    "size": 1,
                    "type": "int16",
                    "registerType": "holdingRegister",
                    "description": "Phase A current grid",
                    "unit": "V",
                    "defaultValue": "0",
                    "staticScaleFactor": -1,
                    "access": "RO"
                },
                {
                    "id": "meterVoltageB",
                    "address": 2618,
                    "size": 1,
                    "type": "uint16",
                    "registerType": "holdingRegister",
                    "description": "Phase B voltage grid",
                    "unit": "V",
                    "defaultValue": "0",
                    "staticScaleFactor": -1,
                    "access": "RO"
                },
                {
                    "id": "meterCurrentB",
                    "address": 2619,
                    "size": 1,
                    "type": "int16",
                    "registerType": "holdingRegister",
                    "description": "Phase B current grid",
                    "unit": "V",
                    "defaultValue": "0",
                    "staticScaleFactor": -1,
                    "access": "RO"
                },
                {
                    "id": "meterVoltageC",
                    "address": 2620,
                    "size": 1,
                    "type": "uint16",
                    "registerType": "holdingRegister",
                    "description": "Phase C voltage grid",
                    "unit": "V",
                    "defaultValue": "0",
                    "staticScaleFactor": -1,
                    "access": "RO"
                },
                {
                    "id": "meterCurrentC",
                    "address": 2621,
                    "size": 1,
                    "type": "int16",
                    "registerType": "holdingRegister",
                    "description": "Phase C current grid",
                    "unit": "V",
                    "defaultValue": "0",
                    "staticScaleFactor": -1,
                    "access": "RO"
                },
                {
                    "id": "dummy6",
                    "address": 2622,
                    "size": 12,
                    "type": "raw",
                    "registerType": "holdingRegister",
                    "description": "none",
                    "access": "RO"
                },
                {
                    "id": "meterTotalEnergyConsumed",
                    "address": 2634,
                    "size": 2,
                    "type": "uint32",
                    "registerType": "holdingRegister",
                    "description": "total energy from grid",
                    "staticScaleFactor": -2,
                    "unit": "kWh",
                    "defaultValue": "0",
                    "access": "RO"
                },
                {
                    "id": "meterTotalEnergyProduced",
                    "address": 2636,
                    "size": 2,
                    "type": "uint32",
                    "registerType": "holdingRegister",
                    "description": "total energy to grid",
                    "staticScaleFactor": -2,
                    "unit": "kWh",
                    "defaultValue": "0",
                    "access": "RO"
                },
                {
                    "id": "dummy7",
                    "address": 2638,
                    "size": 6,
                    "type": "raw",
                    "registerType": "holdingRegister",
                    "description": "none",
                    "access": "RO"
                },
                {
                    "id": "meterFrequency",
                    "address": 2644,
                    "size": 1,
                    "type": "uint16",
                    "registerType": "holdingRegister",
                    "description": "AC frequency grid",
                    "unit": "Hz",
                    "defaultValue": "0",
                    "staticScaleFactor": -2,
                    "access": "RO"
                }
            ]
        }
    ],
    "registers": [
        {
            "id": "serialNumber",
            "address": 800,
            "size": 6,
            "type": "string",
            "readSchedule": "init",
            "registerType": "holdingRegister",
            "description": "Serial number",
            "access": "RO"
        }
    ]
}
